setup.py
aKountable/__init__.py
aKountable/aKountable.py
aKountable.egg-info/PKG-INFO
aKountable.egg-info/SOURCES.txt
aKountable.egg-info/dependency_links.txt
aKountable.egg-info/not-zip-safe
aKountable.egg-info/requires.txt
aKountable.egg-info/top_level.txt