Metadata-Version: 1.1
Name: aKountable
Version: 2.0.0
Summary: aKountable: Safe, accountable AI in the Blockchain
Home-page: https://github.com/safer41/aKountable.git
Author: 41
Author-email: UNKNOWN
License: Apache 2.0
Keywords: AI,blockchain,safety,saferAI
Platform: UNKNOWN
Classifier: Intended Audience :: Developers
Classifier: Intended Audience :: Science/Research
Classifier: License :: OSI Approved :: Apache Software License
Classifier: Programming Language :: Python :: 2.7
